chess_features/__init__.py
chess_features/chess_features.py
chess_features/extractor_factory.py
chess_features/extractors.py
chess_features/neighborhood_transform.py
chess_features/stockfish_features.py
chess_features/transformer.py
chess_features-0.5.0.dist-info/LICENSE
chess_features-0.5.0.dist-info/WHEEL
chess_features-0.5.0.dist-info/METADATA
chess_features-0.5.0.dist-info/RECORD
