Metadata-Version: 2.1
Name: chess_features
Version: 0.5.0
Summary: Transform chess positions to various encodings
Keywords: chess,encoding,features
Author-email: Joel Ewig <joel@familie-ewig.de>
Classifier: License :: OSI Approved :: GNU General Public License v3 or later (GPLv3+)
Requires-Dist: chess>=1.0.0
